rtl/lfsr_scrambler.sv
// Brendan Lynskey 2025
`default_nettype none

module lfsr_scrambler #(
    parameter WIDTH = 7,
    parameter logic [WIDTH-1:0] TAPS = 7'b1000001,
    parameter logic [WIDTH-1:0] SEED = {WIDTH{1'b1}},
    parameter MODE = 0  // 0 = scramble, 1 = descramble
)(
    input  logic clk,
    input  logic rst,
    input  logic en,
    input  logic data_in,
    output logic data_out
);

    logic [WIDTH-1:0] shift_reg;
    logic              feedback;

    // Additive scrambler feedback: XOR of tapped positions
    always_comb begin
        feedback = ^(shift_reg & TAPS);
    end

    always_ff @(posedge clk) begin
        if (rst) begin
            shift_reg <= SEED;
        end else if (en) begin
            if (MODE == 0) begin
                // Scramble mode: shift in the feedback XOR data_in result
                shift_reg <= {shift_reg[WIDTH-2:0], (data_in ^ feedback)};
            end else begin
                // Descramble mode: shift in the received data_in
                shift_reg <= {shift_reg[WIDTH-2:0], data_in};
            end
        end
    end

    // Output is data XOR feedback for both modes (additive scrambler)
    assign data_out = data_in ^ feedback;

endmodule

`default_nettype wire

tb/tb_lfsr_scrambler.sv
// Brendan Lynskey 2025
`default_nettype none
`timescale 1ns / 1ps

module tb_lfsr_scrambler;

    localparam WIDTH = 7;
    localparam logic [WIDTH-1:0] TAPS = 7'b1000001;  // x^7 + x^6 + 1
    localparam logic [WIDTH-1:0] SEED = 7'b1111111;
    localparam NUM_BITS = 64;

    logic clk;
    logic rst;
    logic en;

    // Scrambler signals
    logic scram_data_in;
    logic scram_data_out;

    // Descrambler signals
    logic descram_data_out;

    integer total_tests = 0;
    integer pass_count  = 0;
    integer fail_count  = 0;

    task check_bit(input string name, input logic actual, expected);
        total_tests++;
        if (actual === expected) begin
            pass_count++;
            $display("[PASS] %s", name);
        end else begin
            fail_count++;
            $display("[FAIL] %s: got %b, expected %b", name, actual, expected);
        end
    endtask

    // Scrambler instance (MODE = 0)
    lfsr_scrambler #(
        .WIDTH (WIDTH),
        .TAPS  (TAPS),
        .SEED  (SEED),
        .MODE  (0)
    ) u_scrambler (
        .clk      (clk),
        .rst      (rst),
        .en       (en),
        .data_in  (scram_data_in),
        .data_out (scram_data_out)
    );

    // Descrambler instance (MODE = 1)
    lfsr_scrambler #(
        .WIDTH (WIDTH),
        .TAPS  (TAPS),
        .SEED  (SEED),
        .MODE  (1)
    ) u_descrambler (
        .clk      (clk),
        .rst      (rst),
        .en       (en),
        .data_in  (scram_data_out),
        .data_out (descram_data_out)
    );

    // Clock generation
    initial clk = 0;
    always #5 clk = ~clk;

    // Test data patterns
    logic [NUM_BITS-1:0] test_data;
    logic [NUM_BITS-1:0] recovered_data;
    logic [NUM_BITS-1:0] scrambled_data;
    integer bit_idx;

    initial begin
        $dumpfile("tb_lfsr_scrambler.vcd");
        $dumpvars(0, tb_lfsr_scrambler);

        // -------------------------------------------------------
        // Test 1: Known data pattern — alternating bits
        // -------------------------------------------------------
        $display("--- Test pattern: alternating 10101010... ---");
        test_data = 64'hAAAA_AAAA_AAAA_AAAA;

        rst = 1;
        en  = 0;
        scram_data_in = 0;

        @(posedge clk);
        @(posedge clk);
        rst = 0;
        en  = 1;

        // Feed data through scrambler -> descrambler pipeline
        for (bit_idx = 0; bit_idx < NUM_BITS; bit_idx++) begin
            scram_data_in = test_data[bit_idx];
            @(posedge clk);
            @(negedge clk);
            recovered_data[bit_idx] = descram_data_out;
            scrambled_data[bit_idx] = scram_data_out;
        end

        // Verify round-trip
        total_tests++;
        if (recovered_data === test_data) begin
            pass_count++;
            $display("[PASS] Round-trip: alternating pattern recovered correctly");
        end else begin
            fail_count++;
            $display("[FAIL] Round-trip: alternating pattern mismatch");
            $display("       Sent:      %h", test_data);
            $display("       Recovered: %h", recovered_data);
        end

        // Verify scrambled data differs from input
        total_tests++;
        if (scrambled_data !== test_data) begin
            pass_count++;
            $display("[PASS] Scrambled data differs from input");
        end else begin
            fail_count++;
            $display("[FAIL] Scrambled data is same as input (no scrambling)");
        end

        // -------------------------------------------------------
        // Test 2: All zeros
        // -------------------------------------------------------
        $display("--- Test pattern: all zeros ---");
        test_data = 64'h0;

        rst = 1;
        en  = 0;
        scram_data_in = 0;

        @(posedge clk);
        @(posedge clk);
        rst = 0;
        en  = 1;

        for (bit_idx = 0; bit_idx < NUM_BITS; bit_idx++) begin
            scram_data_in = test_data[bit_idx];
            @(posedge clk);
            @(negedge clk);
            recovered_data[bit_idx] = descram_data_out;
            scrambled_data[bit_idx] = scram_data_out;
        end

        total_tests++;
        if (recovered_data === test_data) begin
            pass_count++;
            $display("[PASS] Round-trip: all-zeros pattern recovered correctly");
        end else begin
            fail_count++;
            $display("[FAIL] Round-trip: all-zeros pattern mismatch");
        end

        // All-zeros through scrambler should produce non-zero output (LFSR sequence)
        total_tests++;
        if (scrambled_data !== 64'h0) begin
            pass_count++;
            $display("[PASS] Scrambler produces non-zero output for zero input");
        end else begin
            fail_count++;
            $display("[FAIL] Scrambler produced all-zero output for zero input");
        end

        // -------------------------------------------------------
        // Test 3: All ones
        // -------------------------------------------------------
        $display("--- Test pattern: all ones ---");
        test_data = 64'hFFFF_FFFF_FFFF_FFFF;

        rst = 1;
        en  = 0;
        scram_data_in = 0;

        @(posedge clk);
        @(posedge clk);
        rst = 0;
        en  = 1;

        for (bit_idx = 0; bit_idx < NUM_BITS; bit_idx++) begin
            scram_data_in = test_data[bit_idx];
            @(posedge clk);
            @(negedge clk);
            recovered_data[bit_idx] = descram_data_out;
        end

        total_tests++;
        if (recovered_data === test_data) begin
            pass_count++;
            $display("[PASS] Round-trip: all-ones pattern recovered correctly");
        end else begin
            fail_count++;
            $display("[FAIL] Round-trip: all-ones pattern mismatch");
        end

        // -------------------------------------------------------
        // Test 4: Pseudo-random pattern
        // -------------------------------------------------------
        $display("--- Test pattern: pseudo-random ---");
        test_data = 64'hDEAD_BEEF_CAFE_BABE;

        rst = 1;
        en  = 0;
        scram_data_in = 0;

        @(posedge clk);
        @(posedge clk);
        rst = 0;
        en  = 1;

        for (bit_idx = 0; bit_idx < NUM_BITS; bit_idx++) begin
            scram_data_in = test_data[bit_idx];
            @(posedge clk);
            @(negedge clk);
            recovered_data[bit_idx] = descram_data_out;
        end

        total_tests++;
        if (recovered_data === test_data) begin
            pass_count++;
            $display("[PASS] Round-trip: pseudo-random pattern recovered correctly");
        end else begin
            fail_count++;
            $display("[FAIL] Round-trip: pseudo-random pattern mismatch");
            $display("       Sent:      %h", test_data);
            $display("       Recovered: %h", recovered_data);
        end

        $display("");
        $display("=== Scrambler Testbench Summary ===");
        $display("Tests: %0d | Pass: %0d | Fail: %0d", total_tests, pass_count, fail_count);
        $finish;
    end

endmodule

`default_nettype wire

sim/tb_lfsr_scrambler.vcd
$date
	Fri Mar 20 08:57:13 2026
$end
$version
	Icarus Verilog
$end
$timescale
	1ps
$end
$scope module tb_lfsr_scrambler $end
$var wire 1 ! scram_data_out $end
$var wire 1 " descram_data_out $end
$var parameter 32 # NUM_BITS $end
$var parameter 7 $ SEED $end
$var parameter 7 % TAPS $end
$var parameter 32 & WIDTH $end
$var reg 1 ' clk $end
$var reg 1 ( en $end
$var reg 64 ) recovered_data [63:0] $end
$var reg 1 * rst $end
$var reg 1 + scram_data_in $end
$var reg 64 , scrambled_data [63:0] $end
$var reg 64 - test_data [63:0] $end
$var integer 32 . bit_idx [31:0] $end
$var integer 32 / fail_count [31:0] $end
$var integer 32 0 pass_count [31:0] $end
$var integer 32 1 total_tests [31:0] $end
$scope module u_descrambler $end
$var wire 1 ' clk $end
$var wire 1 " data_out $end
$var wire 1 ( en $end
$var wire 1 * rst $end
$var wire 1 ! data_in $end
$var parameter 32 2 MODE $end
$var parameter 7 3 SEED $end
$var parameter 7 4 TAPS $end
$var parameter 32 5 WIDTH $end
$var reg 1 6 feedback $end
$var reg 7 7 shift_reg [6:0] $end
$upscope $end
$scope module u_scrambler $end
$var wire 1 ' clk $end
$var wire 1 + data_in $end
$var wire 1 ! data_out $end
$var wire 1 ( en $end
$var wire 1 * rst $end
$var parameter 32 8 MODE $end
$var parameter 7 9 SEED $end
$var parameter 7 : TAPS $end
$var parameter 32 ; WIDTH $end
$var reg 1 < feedback $end
$var reg 7 = shift_reg [6:0] $end
$upscope $end
$scope task check_bit $end
$var reg 1 > actual $end
$var reg 1 ? expected $end
$upscope $end
$upscope $end
$enddefinitions $end
$comment Show the parameter values. $end
$dumpall
b111 ;
b1000001 :
b1111111 9
b0 8
b111 5
b1000001 4
b1111111 3
b1 2
b111 &
b1000001 %
b1111111 $
b1000000 #
$end
#0
$dumpvars
x?
x>
bx =
x<
bx 7
x6
b0 1
b0 0
b0 /
bx .
b1010101010101010101010101010101010101010101010101010101010101010 -
bx ,
0+
1*
bx )
0(
0'
x"
x!
$end
#5000
0"
0!
0<
06
b1111111 =
b1111111 7
1'
#10000
0'
#15000
b0 .
1(
0*
1'
#20000
0'
#25000
1!
0"
1<
16
b1111110 =
b1111110 7
1'
#30000
1"
0!
1+
b1 .
bx1 ,
bx0 )
0'
#35000
b1111100 7
b1111100 =
1'
#40000
0"
1!
0+
b10 .
bx01 ,
bx10 )
0'
#45000
0!
0"
0<
06
b1111001 =
b1111001 7
1'
#50000
1"
1!
1+
b11 .
bx001 ,
bx010 )
0'
#55000
b1110011 7
b1110011 =
1'
#60000
0"
0!
0+
b100 .
bx1001 ,
bx1010 )
0'
#65000
1!
0"
1<
16
b1100110 =
b1100110 7
1'
#70000
1"
0!
1+
b101 .
bx11001 ,
bx01010 )
0'
#75000
b1001100 7
b1001100 =
1'
#80000
0"
1!
0+
b110 .
bx011001 ,
bx101010 )
0'
#85000
b11001 =
b11001 7
1'
#90000
1"
0!
1+
b111 .
bx1011001 ,
bx0101010 )
0'
#95000
1!
06
0<
b110010 7
b110010 =
1'
#100000
0"
0!
0+
b1000 .
bx11011001 ,
bx10101010 )
0'
#105000
1!
0"
1<
16
b1100100 =
b1100100 7
1'
#110000
1"
0!
1+
b1001 .
bx111011001 ,
bx010101010 )
0'
#115000
b1001000 7
b1001000 =
1'
#120000
0"
1!
0+
b1010 .
bx0111011001 ,
bx1010101010 )
0'
#125000
b10001 =
b10001 7
1'
#130000
1"
0!
1+
b1011 .
bx10111011001 ,
bx01010101010 )
0'
#135000
1!
06
0<
b100010 7
b100010 =
1'
#140000
0"
0!
0+
b1100 .
bx110111011001 ,
bx101010101010 )
0'
#145000
1!
0"
1<
16
b1000100 =
b1000100 7
1'
#150000
1"
0!
1+
b1101 .
bx1110111011001 ,
bx0101010101010 )
0'
#155000
1!
06
0<
b1000 7
b1000 =
1'
#160000
0"
0!
0+
b1110 .
bx11110111011001 ,
bx10101010101010 )
0'
#165000
b10000 =
b10000 7
1'
#170000
1"
1!
1+
b1111 .
bx011110111011001 ,
bx010101010101010 )
0'
#175000
0!
16
1<
b100001 7
b100001 =
1'
#180000
0"
1!
0+
b10000 .
bx0011110111011001 ,
bx1010101010101010 )
0'
#185000
0!
0"
0<
06
b1000011 =
b1000011 7
1'
#190000
1"
1!
1+
b10001 .
bx00011110111011001 ,
bx01010101010101010 )
0'
#195000
0!
16
1<
b111 7
b111 =
1'
#200000
0"
1!
0+
b10010 .
bx000011110111011001 ,
bx101010101010101010 )
0'
#205000
b1111 =
b1111 7
1'
#210000
1"
0!
1+
b10011 .
bx1000011110111011001 ,
bx0101010101010101010 )
0'
#215000
1!
06
0<
b11110 7
b11110 =
1'
#220000
0"
0!
0+
b10100 .
bx11000011110111011001 ,
bx10101010101010101010 )
0'
#225000
b111100 =
b111100 7
1'
#230000
1"
1!
1+
b10101 .
bx011000011110111011001 ,
bx010101010101010101010 )
0'
#235000
b1111001 7
b1111001 =
1'
#240000
0"
0!
0+
b10110 .
bx1011000011110111011001 ,
bx1010101010101010101010 )
0'
#245000
1!
0"
1<
16
b1110010 =
b1110010 7
1'
#250000
1"
0!
1+
b10111 .
bx11011000011110111011001 ,
bx01010101010101010101010 )
0'
#255000
b1100100 7
b1100100 =
1'
#260000
0"
1!
0+
b11000 .
bx011011000011110111011001 ,
bx101010101010101010101010 )
0'
#265000
0!
0"
0<
06
b1001001 =
b1001001 7
1'
#270000
1"
1!
1+
b11001 .
bx0011011000011110111011001 ,
bx0101010101010101010101010 )
0'
#275000
0!
16
1<
b10011 7
b10011 =
1'
#280000
0"
1!
0+
b11010 .
bx00011011000011110111011001 ,
bx10101010101010101010101010 )
0'
#285000
b100111 =
b100111 7
1'
#290000
1"
0!
1+
b11011 .
bx100011011000011110111011001 ,
bx010101010101010101010101010 )
0'
#295000
b1001110 7
b1001110 =
1'
#300000
0"
1!
0+
b11100 .
bx0100011011000011110111011001 ,
bx1010101010101010101010101010 )
0'
#305000
b11101 =
b11101 7
1'
#310000
1"
0!
1+
b11101 .
bx10100011011000011110111011001 ,
bx01010101010101010101010101010 )
0'
#315000
1!
06
0<
b111010 7
b111010 =
1'
#320000
0"
0!
0+
b11110 .
bx110100011011000011110111011001 ,
bx101010101010101010101010101010 )
0'
#325000
1!
0"
1<
16
b1110100 =
b1110100 7
1'
#330000
1"
0!
1+
b11111 .
bx1110100011011000011110111011001 ,
bx0101010101010101010101010101010 )
0'
#335000
b1101000 7
b1101000 =
1'
#340000
0"
1!
0+
b100000 .
bx01110100011011000011110111011001 ,
bx10101010101010101010101010101010 )
0'
#345000
0!
0"
0<
06
b1010001 =
b1010001 7
1'
#350000
1"
1!
1+
b100001 .
bx001110100011011000011110111011001 ,
bx010101010101010101010101010101010 )
0'
#355000
0!
16
1<
b100011 7
b100011 =
1'
#360000
0"
1!
0+
b100010 .
bx0001110100011011000011110111011001 ,
bx1010101010101010101010101010101010 )
0'
#365000
0!
0"
0<
06
b1000111 =
b1000111 7
1'
#370000
1"
1!
1+
b100011 .
bx00001110100011011000011110111011001 ,
bx01010101010101010101010101010101010 )
0'
#375000
0!
16
1<
b1111 7
b1111 =
1'
#380000
0"
1!
0+
b100100 .
bx000001110100011011000011110111011001 ,
bx101010101010101010101010101010101010 )
0'
#385000
b11111 =
b11111 7
1'
#390000
1"
0!
1+
b100101 .
bx1000001110100011011000011110111011001 ,
bx0101010101010101010101010101010101010 )
0'
#395000
1!
06
0<
b111110 7
b111110 =
1'
#400000
0"
0!
0+
b100110 .
bx11000001110100011011000011110111011001 ,
bx10101010101010101010101010101010101010 )
0'
#405000
1!
0"
1<
16
b1111100 =
b1111100 7
1'
#410000
1"
0!
1+
b100111 .
bx111000001110100011011000011110111011001 ,
bx010101010101010101010101010101010101010 )
0'
#415000
b1111000 7
b1111000 =
1'
#420000
0"
1!
0+
b101000 .
bx0111000001110100011011000011110111011001 ,
bx1010101010101010101010101010101010101010 )
0'
#425000
0!
0"
0<
06
b1110001 =
b1110001 7
1'
#430000
1"
1!
1+
b101001 .
bx00111000001110100011011000011110111011001 ,
bx01010101010101010101010101010101010101010 )
0'
#435000
b1100011 7
b1100011 =
1'
#440000
0"
0!
0+
b101010 .
bx100111000001110100011011000011110111011001 ,
bx101010101010101010101010101010101010101010 )
0'
#445000
1!
0"
1<
16
b1000110 =
b1000110 7
1'
#450000
1"
0!
1+
b101011 .
bx1100111000001110100011011000011110111011001 ,
bx0101010101010101010101010101010101010101010 )
0'
#455000
1!
06
0<
b1100 7
b1100 =
1'
#460000
0"
0!
0+
b101100 .
bx11100111000001110100011011000011110111011001 ,
bx10101010101010101010101010101010101010101010 )
0'
#465000
b11000 =
b11000 7
1'
#470000
1"
1!
1+
b101101 .
bx011100111000001110100011011000011110111011001 ,
bx010101010101010101010101010101010101010101010 )
0'
#475000
0!
16
1<
b110001 7
b110001 =
1'
#480000
0"
1!
0+
b101110 .
bx0011100111000001110100011011000011110111011001 ,
bx1010101010101010101010101010101010101010101010 )
0'
#485000
0!
0"
0<
06
b1100011 =
b1100011 7
1'
#490000
1"
1!
1+
b101111 .
bx00011100111000001110100011011000011110111011001 ,
bx01010101010101010101010101010101010101010101010 )
0'
#495000
b1000111 7
b1000111 =
1'
#500000
0"
0!
0+
b110000 .
bx100011100111000001110100011011000011110111011001 ,
bx101010101010101010101010101010101010101010101010 )
0'
#505000
b1110 =
b1110 7
1'
#510000
1"
1!
1+
b110001 .
bx0100011100111000001110100011011000011110111011001 ,
bx0101010101010101010101010101010101010101010101010 )
0'
#515000
0!
16
1<
b11101 7
b11101 =
1'
#520000
0"
1!
0+
b110010 .
bx00100011100111000001110100011011000011110111011001 ,
bx10101010101010101010101010101010101010101010101010 )
0'
#525000
b111011 =
b111011 7
1'
#530000
1"
0!
1+
b110011 .
bx100100011100111000001110100011011000011110111011001 ,
bx010101010101010101010101010101010101010101010101010 )
0'
#535000
b1110110 7
b1110110 =
1'
#540000
0"
1!
0+
b110100 .
bx0100100011100111000001110100011011000011110111011001 ,
bx1010101010101010101010101010101010101010101010101010 )
0'
#545000
0!
0"
0<
06
b1101101 =
b1101101 7
1'
#550000
1"
1!
1+
b110101 .
bx00100100011100111000001110100011011000011110111011001 ,
bx01010101010101010101010101010101010101010101010101010 )
0'
#555000
b1011011 7
b1011011 =
1'
#560000
0"
0!
0+
b110110 .
bx100100100011100111000001110100011011000011110111011001 ,
bx101010101010101010101010101010101010101010101010101010 )
0'
#565000
b110110 =
b110110 7
1'
#570000
1"
1!
1+
b110111 .
bx0100100100011100111000001110100011011000011110111011001 ,
bx0101010101010101010101010101010101010101010101010101010 )
0'
#575000
b1101101 7
b1101101 =
1'
#580000
0"
0!
0+
b111000 .
bx10100100100011100111000001110100011011000011110111011001 ,
bx10101010101010101010101010101010101010101010101010101010 )
0'
#585000
1!
0"
1<
16
b1011010 =
b1011010 7
1'
#590000
1"
0!
1+
b111001 .
bx110100100100011100111000001110100011011000011110111011001 ,
bx010101010101010101010101010101010101010101010101010101010 )
0'
#595000
1!
06
0<
b110100 7
b110100 =
1'
#600000
0"
0!
0+
b111010 .
bx1110100100100011100111000001110100011011000011110111011001 ,
bx1010101010101010101010101010101010101010101010101010101010 )
0'
#605000
1!
0"
1<
16
b1101000 =
b1101000 7
1'
#610000
1"
0!
1+
b111011 .
bx11110100100100011100111000001110100011011000011110111011001 ,
bx01010101010101010101010101010101010101010101010101010101010 )
0'
#615000
b1010000 7
b1010000 =
1'
#620000
0"
1!
0+
b111100 .
bx011110100100100011100111000001110100011011000011110111011001 ,
bx101010101010101010101010101010101010101010101010101010101010 )
0'
#625000
b100001 =
b100001 7
1'
#630000
1"
0!
1+
b111101 .
bx1011110100100100011100111000001110100011011000011110111011001 ,
bx0101010101010101010101010101010101010101010101010101010101010 )
0'
#635000
b1000010 7
b1000010 =
1'
#640000
0"
1!
0+
b111110 .
bx01011110100100100011100111000001110100011011000011110111011001 ,
bx10101010101010101010101010101010101010101010101010101010101010 )
0'
#645000
b101 =
b101 7
1'
#650000
1"
0!
1+
b111111 .
bx101011110100100100011100111000001110100011011000011110111011001 ,
bx010101010101010101010101010101010101010101010101010101010101010 )
0'
#655000
1!
06
0<
b1010 7
b1010 =
1'
#660000
0"
0!
0+
0(
1*
b0 -
b10 0
b10 1
b1000000 .
b1101011110100100100011100111000001110100011011000011110111011001 ,
b1010101010101010101010101010101010101010101010101010101010101010 )
0'
#665000
b1111111 =
b1111111 7
1'
#670000
0'
#675000
b0 .
1(
0*
1'
#680000
0'
#685000
1!
0"
1<
16
b1111110 =
b1111110 7
1'
#690000
b1 .
0'
#695000
0!
06
0<
b1111101 7
b1111101 =
1'
#700000
b10 .
b1010101010101010101010101010101010101010101010101010101010101000 )
0'
#705000
1!
0"
1<
16
b1111010 =
b1111010 7
1'
#710000
b11 .
b1101011110100100100011100111000001110100011011000011110111011101 ,
0'
#715000
0!
06
0<
b1110101 7
b1110101 =
1'
#720000
b100 .
b1101011110100100100011100111000001110100011011000011110111010101 ,
b1010101010101010101010101010101010101010101010101010101010100000 )
0'
#725000
1!
0"
1<
16
b1101010 =
b1101010 7
1'
#730000
b101 .
0'
#735000
0!
06
0<
b1010101 7
b1010101 =
1'
#740000
b110 .
b1010101010101010101010101010101010101010101010101010101010000000 )
0'
#745000
b101010 =
b101010 7
1'
#750000
b111 .
b1101011110100100100011100111000001110100011011000011110110010101 ,
0'
#755000
1!
16
1<
b1010100 7
b1010100 =
1'
#760000
b1000 .
b1010101010101010101010101010101010101010101010101010101000000000 )
0'
#765000
b101001 =
b101001 7
1'
#770000
b1001 .
0'
#775000
0!
06
0<
b1010011 7
b1010011 =
1'
#780000
b1010 .
b1010101010101010101010101010101010101010101010101010100000000000 )
0'
#785000
b100110 =
b100110 7
1'
#790000
b1011 .
b1101011110100100100011100111000001110100011011000011100110010101 ,
0'
#795000
1!
16
1<
b1001100 7
b1001100 =
1'
#800000
b1100 .
b1010101010101010101010101010101010101010101010101010000000000000 )
0'
#805000
b11001 =
b11001 7
1'
#810000
b1101 .
0'
#815000
b110011 7
b110011 =
1'
#820000
b1110 .
b1010101010101010101010101010101010101010101010101000000000000000 )
0'
#825000
0!
0"
0<
06
b1100111 =
b1100111 7
1'
#830000
b1111 .
0'
#835000
1!
16
1<
b1001110 7
b1001110 =
1'
#840000
b10000 .
b1101011110100100100011100111000001110100011011001011100110010101 ,
b1010101010101010101010101010101010101010101010100000000000000000 )
0'
#845000
b11101 =
b11101 7
1'
#850000
b10001 .
b1101011110100100100011100111000001110100011011011011100110010101 ,
0'
#855000
b111011 7
b111011 =
1'
#860000
b10010 .
b1101011110100100100011100111000001110100011011111011100110010101 ,
b1010101010101010101010101010101010101010101010000000000000000000 )
0'
#865000
0!
0"
0<
06
b1110111 =
b1110111 7
1'
#870000
b10011 .
b1101011110100100100011100111000001110100011010111011100110010101 ,
0'
#875000
1!
16
1<
b1101110 7
b1101110 =
1'
#880000
b10100 .
b1010101010101010101010101010101010101010101000000000000000000000 )
0'
#885000
0!
0"
0<
06
b1011101 =
b1011101 7
1'
#890000
b10101 .
0'
#895000
b111010 7
b111010 =
1'
#900000
b10110 .
b1101011110100100100011100111000001110100010010111011100110010101 ,
b1010101010101010101010101010101010101010100000000000000000000000 )
0'
#905000
1!
0"
1<
16
b1110100 =
b1110100 7
1'
#910000
b10111 .
0'
#915000
0!
06
0<
b1101001 7
b1101001 =
1'
#920000
b11000 .
b1010101010101010101010101010101010101010000000000000000000000000 )
0'
#925000
1!
0"
1<
16
b1010010 =
b1010010 7
1'
#930000
b11001 .
b1101011110100100100011100111000001110101010010111011100110010101 ,
0'
#935000
b100101 7
b100101 =
1'
#940000
b11010 .
b1101011110100100100011100111000001110111010010111011100110010101 ,
b1010101010101010101010101010101010101000000000000000000000000000 )
0'
#945000
0!
0"
0<
06
b1001011 =
b1001011 7
1'
#950000
b11011 .
b1101011110100100100011100111000001110011010010111011100110010101 ,
0'
#955000
b10110 7
b10110 =
1'
#960000
b11100 .
b1010101010101010101010101010101010100000000000000000000000000000 )
0'
#965000
b101100 =
b101100 7
1'
#970000
b11101 .
b1101011110100100100011100111000001100011010010111011100110010101 ,
0'
#975000
1!
16
1<
b1011000 7
b1011000 =
1'
#980000
b11110 .
b1010101010101010101010101010101010000000000000000000000000000000 )
0'
#985000
b110001 =
b110001 7
1'
#990000
b11111 .
0'
#995000
0!
06
0<
b1100011 7
b1100011 =
1'
#1000000
b100000 .
b1010101010101010101010101010101000000000000000000000000000000000 )
0'
#1005000
1!
0"
1<
16
b1000110 =
b1000110 7
1'
#1010000
b100001 .
b1101011110100100100011100111000101100011010010111011100110010101 ,
0'
#1015000
b1101 7
b1101 =
1'
#1020000
b100010 .
b1101011110100100100011100111001101100011010010111011100110010101 ,
b1010101010101010101010101010100000000000000000000000000000000000 )
0'
#1025000
b11011 =
b11011 7
1'
#1030000
b100011 .
b1101011110100100100011100111011101100011010010111011100110010101 ,
0'
#1035000
b110111 7
b110111 =
1'
#1040000
b100100 .
b1101011110100100100011100111111101100011010010111011100110010101 ,
b1010101010101010101010101010000000000000000000000000000000000000 )
0'
#1045000
0!
0"
0<
06
b1101111 =
b1101111 7
1'
#1050000
b100101 .
b1101011110100100100011100110111101100011010010111011100110010101 ,
0'
#1055000
1!
16
1<
b1011110 7
b1011110 =
1'
#1060000
b100110 .
b1010101010101010101010101000000000000000000000000000000000000000 )
0'
#1065000
b111101 =
b111101 7
1'
#1070000
b100111 .
0'
#1075000
0!
06
0<
b1111011 7
b1111011 =
1'
#1080000
b101000 .
b1010101010101010101010100000000000000000000000000000000000000000 )
0'
#1085000
1!
0"
1<
16
b1110110 =
b1110110 7
1'
#1090000
b101001 .
b1101011110100100100011110110111101100011010010111011100110010101 ,
0'
#1095000
0!
06
0<
b1101101 7
b1101101 =
1'
#1100000
b101010 .
b1101011110100100100011010110111101100011010010111011100110010101 ,
b1010101010101010101010000000000000000000000000000000000000000000 )
0'
#1105000
1!
0"
1<
16
b1011010 =
b1011010 7
1'
#1110000
b101011 .
0'
#1115000
b110101 7
b110101 =
1'
#1120000
b101100 .
b1010101010101010101000000000000000000000000000000000000000000000 )
0'
#1125000
0!
0"
0<
06
b1101011 =
b1101011 7
1'
#1130000
b101101 .
0'
#1135000
1!
16
1<
b1010110 7
b1010110 =
1'
#1140000
b101110 .
b1101011110100100101011010110111101100011010010111011100110010101 ,
b1010101010101010100000000000000000000000000000000000000000000000 )
0'
#1145000
b101101 =
b101101 7
1'
#1150000
b101111 .
b1101011110100100111011010110111101100011010010111011100110010101 ,
0'
#1155000
0!
06
0<
b1011011 7
b1011011 =
1'
#1160000
b110000 .
b1101011110100100011011010110111101100011010010111011100110010101 ,
b1010101010101010000000000000000000000000000000000000000000000000 )
0'
#1165000
b110110 =
b110110 7
1'
#1170000
b110001 .
0'
#1175000
1!
16
1<
b1101100 7
b1101100 =
1'
#1180000
b110010 .
b1101011110100110011011010110111101100011010010111011100110010101 ,
b1010101010101000000000000000000000000000000000000000000000000000 )
0'
#1185000
0!
0"
0<
06
b1011001 =
b1011001 7
1'
#1190000
b110011 .
b1101011110100010011011010110111101100011010010111011100110010101 ,
0'
#1195000
b110010 7
b110010 =
1'
#1200000
b110100 .
b1010101010100000000000000000000000000000000000000000000000000000 )
0'
#1205000
1!
0"
1<
16
b1100100 =
b1100100 7
1'
#1210000
b110101 .
b1101011110110010011011010110111101100011010010111011100110010101 ,
0'
#1215000
0!
06
0<
b1001001 7
b1001001 =
1'
#1220000
b110110 .
b1101011110010010011011010110111101100011010010111011100110010101 ,
b1010101010000000000000000000000000000000000000000000000000000000 )
0'
#1225000
b10010 =
b10010 7
1'
#1230000
b110111 .
0'
#1235000
b100100 7
b100100 =
1'
#1240000
b111000 .
b1101011100010010011011010110111101100011010010111011100110010101 ,
b1010101000000000000000000000000000000000000000000000000000000000 )
0'
#1245000
1!
0"
1<
16
b1001000 =
b1001000 7
1'
#1250000
b111001 .
0'
#1255000
b10001 7
b10001 =
1'
#1260000
b111010 .
b1010100000000000000000000000000000000000000000000000000000000000 )
0'
#1265000
b100011 =
b100011 7
1'
#1270000
b111011 .
0'
#1275000
0!
06
0<
b1000111 7
b1000111 =
1'
#1280000
b111100 .
b1010000000000000000000000000000000000000000000000000000000000000 )
0'
#1285000
b1110 =
b1110 7
1'
#1290000
b111101 .
b1100011100010010011011010110111101100011010010111011100110010101 ,
0'
#1295000
b11100 7
b11100 =
1'
#1300000
b111110 .
b1000000000000000000000000000000000000000000000000000000000000000 )
0'
#1305000
b111000 =
b111000 7
1'
#1310000
b111111 .
b1000011100010010011011010110111101100011010010111011100110010101 ,
0'
#1315000
1!
16
1<
b1110000 7
b1110000 =
1'
#1320000
0(
1*
b1111111111111111111111111111111111111111111111111111111111111111 -
b100 0
b100 1
b1000000 .
b0 )
0'
#1325000
0!
0"
0<
06
b1111111 =
b1111111 7
1'
#1330000
0'
#1335000
1"
1!
1+
b0 .
1(
0*
1'
#1340000
0'
#1345000
1'
#1350000
b1 .
b1 )
0'
#1355000
1'
#1360000
b10 .
b11 )
0'
#1365000
1'
#1370000
b11 .
b111 )
0'
#1375000
1'
#1380000
b100 .
b1111 )
0'
#1385000
1'
#1390000
b101 .
b11111 )
0'
#1395000
1'
#1400000
b110 .
b111111 )
0'
#1405000
1'
#1410000
b111 .
b1111111 )
0'
#1415000
1'
#1420000
b1000 .
b11111111 )
0'
#1425000
1'
#1430000
b1001 .
b111111111 )
0'
#1435000
1'
#1440000
b1010 .
b1111111111 )
0'
#1445000
1'
#1450000
b1011 .
b11111111111 )
0'
#1455000
1'
#1460000
b1100 .
b111111111111 )
0'
#1465000
1'
#1470000
b1101 .
b1111111111111 )
0'
#1475000
1'
#1480000
b1110 .
b11111111111111 )
0'
#1485000
1'
#1490000
b1111 .
b111111111111111 )
0'
#1495000
1'
#1500000
b10000 .
b1111111111111111 )
0'
#1505000
1'
#1510000
b10001 .
b11111111111111111 )
0'
#1515000
1'
#1520000
b10010 .
b111111111111111111 )
0'
#1525000
1'
#1530000
b10011 .
b1111111111111111111 )
0'
#1535000
1'
#1540000
b10100 .
b11111111111111111111 )
0'
#1545000
1'
#1550000
b10101 .
b111111111111111111111 )
0'
#1555000
1'
#1560000
b10110 .
b1111111111111111111111 )
0'
#1565000
1'
#1570000
b10111 .
b11111111111111111111111 )
0'
#1575000
1'
#1580000
b11000 .
b111111111111111111111111 )
0'
#1585000
1'
#1590000
b11001 .
b1111111111111111111111111 )
0'
#1595000
1'
#1600000
b11010 .
b11111111111111111111111111 )
0'
#1605000
1'
#1610000
b11011 .
b111111111111111111111111111 )
0'
#1615000
1'
#1620000
b11100 .
b1111111111111111111111111111 )
0'
#1625000
1'
#1630000
b11101 .
b11111111111111111111111111111 )
0'
#1635000
1'
#1640000
b11110 .
b111111111111111111111111111111 )
0'
#1645000
1'
#1650000
b11111 .
b1111111111111111111111111111111 )
0'
#1655000
1'
#1660000
b100000 .
b11111111111111111111111111111111 )
0'
#1665000
1'
